eggella/__init__.py
eggella/_patches.py
eggella/_types.py
eggella/app.py
eggella/exceptions.py
eggella/manager.py
eggella/command/__init__.py
eggella/command/abc.py
eggella/command/arg_caster.py
eggella/command/completer.py
eggella/command/handler.py
eggella/command/objects.py
eggella/command/parser.py
eggella/events/__init__.py
eggella/events/abc.py
eggella/events/events.py
eggella/fsm/__init__.py
eggella/fsm/fsm.py
eggella/shortcuts/__init__.py
eggella/shortcuts/cmd_shortcuts.py
eggella/shortcuts/help_pager.py
eggella/tools/__init__.py
eggella/tools/type_caster.py
eggella-0.1.7.dist-info/METADATA
eggella-0.1.7.dist-info/WHEEL
eggella-0.1.7.dist-info/RECORD
