Metadata-Version: 2.1
Name: eggella
Version: 0.1.7
Summary: Create awesome command line applications with less effort
Project-URL: Documentation, https://eggella.readthedocs.io/en/latest/
Project-URL: Source, https://github.com/vypivshiy/eggella
Author: georgiy
License-Expression: MIT
Classifier: Development Status :: 4 - Beta
Classifier: Programming Language :: Python
Classifier: Programming Language :: Python :: 3.8
Classifier: Programming Language :: Python :: 3.9
Classifier: Programming Language :: Python :: 3.10
Classifier: Programming Language :: Python :: 3.11
Classifier: Programming Language :: Python :: Implementation :: CPython
Classifier: Programming Language :: Python :: Implementation :: PyPy
Requires-Python: >=3.8
Requires-Dist: prompt-toolkit
Provides-Extra: dev
Requires-Dist: black; extra == 'dev'
Requires-Dist: isort; extra == 'dev'
Requires-Dist: mypy; extra == 'dev'
Requires-Dist: ruff; extra == 'dev'
